{
	"id": "nEkjNawtJe1KQFV",
	"json": "{\"id\":\"nEkjNawtJe1KQFV\",\"url\":\"https://www.alza.cz/EN/projectors/dlp-projectors/18843306.htm\",\"loadedUrl\":\"https://www.alza.cz/EN/projectors/18843223.htm\",\"uniqueKey\":\"https://www.alza.cz/EN/projectors/dlp-projectors/18843306.htm\",\"method\":\"GET\",\"noRetry\":false,\"retryCount\":0,\"errorMessages\":[],\"headers\":{},\"userData\":{\"label\":\"DETAIL\",\"__crawlee\":{\"crawlDepth\":1,\"enqueueStrategy\":\"same-hostname\",\"state\":4}},\"handledAt\":\"2025-11-19T17:55:49.453Z\"}",
	"method": "GET",
	"orderNo": null,
	"retryCount": 0,
	"uniqueKey": "https://www.alza.cz/EN/projectors/dlp-projectors/18843306.htm",
	"url": "https://www.alza.cz/EN/projectors/dlp-projectors/18843306.htm"
}